emailable/__init__.py
emailable/client.py
emailable/error.py
emailable/response.py
emailable-3.1.0.dist-info/licenses/LICENSE
tests/__init__.py
tests/test_authentication.py
tests/test_client.py
emailable-3.1.0.dist-info/METADATA
emailable-3.1.0.dist-info/WHEEL
emailable-3.1.0.dist-info/top_level.txt
emailable-3.1.0.dist-info/RECORD
