Metadata-Version: 2.4
Name: emailable
Version: 3.1.0
Summary: This is the official python wrapper for the Emailable API.
Home-page: https://github.com/emailable/emailable-python
Author: Emailable
Author-email: support@emailable.com
License: MIT
Project-URL: Bug Tracker, https://github.com/emailable/emailable-python/issues
Project-URL: Documentation, https://emailable.com/docs/api?python
Project-URL: Source Code, https://github.com/emailable/emailable-python
Keywords: emailable email verification
Classifier: Programming Language :: Python :: 3
Classifier: License :: OSI Approved :: MIT License
Classifier: Operating System :: OS Independent
Requires-Python: >=3.6
License-File: LICENSE
Requires-Dist: requests
Dynamic: author
Dynamic: author-email
Dynamic: classifier
Dynamic: description
Dynamic: description-content-type
Dynamic: home-page
Dynamic: keywords
Dynamic: license
Dynamic: license-file
Dynamic: project-url
Dynamic: requires-dist
Dynamic: requires-python
Dynamic: summary
